{
    "sourceFile": "frontend/src/components/Remainder.jsx",
    "activeCommit": 0,
    "commits": [
        {
            "activePatchIndex": 0,
            "patches": [
                {
                    "date": 1741166291279,
                    "content": "Index: \n===================================================================\n--- \n+++ \n"
                }
            ],
            "date": 1741166291279,
            "name": "Commit-0",
            "content": "import React from 'react'\r\n\r\nconst Remainder = () => {\r\n  return (\r\n    <div>\r\n      Remainder  from backend\r\n    </div>\r\n  )\r\n}\r\n\r\nexport default Remainder\r\n"
        }
    ]
}